aceql/__init__.py
aceql/connection.py
aceql/connection_options.py
aceql/cursor.py
aceql/database_info.py
aceql/dbapi2.py
aceql/error.py
aceql/health_check.py
aceql/limits_info.py
aceql/login_url_decoder.py
aceql/progress_indicator.py
aceql/proxy_auth.py
aceql/server_memory_info.py
aceql/sql_null_type.py
aceql/_private/__init__.py
aceql/_private/aceql_batch_api.py
aceql/_private/aceql_blob_api.py
aceql/_private/aceql_blob_upload_api.py
aceql/_private/aceql_debug.py
aceql/_private/aceql_debug_parms.py
aceql/_private/aceql_exec_query_api.py
aceql/_private/aceql_exec_update_api.py
aceql/_private/aceql_execution_util.py
aceql/_private/aceql_health_check_info_api.py
aceql/_private/aceql_http_api.py
aceql/_private/aceql_metadata_api.py
aceql/_private/column_types_builder.py
aceql/_private/connection_util.py
aceql/_private/cursor_util.py
aceql/_private/datetime_util.py
aceql/_private/file_util.py
aceql/_private/framework_debug.py
aceql/_private/http_client_with_retry.py
aceql/_private/result_analyzer.py
aceql/_private/result_set_info.py
aceql/_private/row_counter.py
aceql/_private/row_parser.py
aceql/_private/stream_result_analyzer.py
aceql/_private/type_converter.py
aceql/_private/user_login_store.py
aceql/_private/version_values.py
aceql/_private/batch/__init__.py
aceql/_private/batch/prep_statement_params_holder.py
aceql/_private/batch/update_counts_array_dto.py
aceql/_private/dto/__init__.py
aceql/_private/dto/database_info_dto.py
aceql/_private/dto/health_check_info_dto.py
aceql/_private/dto/jdbc_database_meta_data_dto.py
aceql/_private/dto/limits_info_dto.py
aceql/_private/dto/server_query_executor_dto.py
aceql/_private/dto/server_query_executor_dto_builder.py
aceql/_private/dto/table_dto.py
aceql/_private/dto/table_names_dto.py
aceql/metadata/__init__.py
aceql/metadata/column.py
aceql/metadata/exportedkey.py
aceql/metadata/foreignkey.py
aceql/metadata/importedkey.py
aceql/metadata/index.py
aceql/metadata/jdbc_database_meta_data.py
aceql/metadata/primarykey.py
aceql-5.8.dist-info/LICENSE
aceql-5.8.dist-info/METADATA
aceql-5.8.dist-info/WHEEL
aceql-5.8.dist-info/top_level.txt
aceql-5.8.dist-info/RECORD
