Metadata-Version: 2.1
Name: aceql
Version: 5.8
Summary: Python 3 Client toolkit for easy access of remote SQL databases managed with AceQL HTTP.
Home-page: https://github.com/kawansoft/aceql-py
Author: KawanSoft
Author-email: contact@kawansoft.com
License: Apache 2.0
Keywords: DATABASE SQL HTTP CLIENT-SERVER
Classifier: Development Status :: 5 - Production/Stable
Classifier: License :: OSI Approved :: Apache Software License
Classifier: Programming Language :: Python :: 3.7
Classifier: Programming Language :: Python :: 3.8
Classifier: Programming Language :: Python :: 3.9
Classifier: Programming Language :: Python :: 3.10
Classifier: Programming Language :: Python :: 3.11
Classifier: Programming Language :: Python :: 3.12
Classifier: Topic :: Database
Classifier: Topic :: Software Development :: Libraries :: Application Frameworks
License-File: LICENSE
Requires-Dist: requests <3.0.0,>=2.18.4
Requires-Dist: requests-toolbelt >=0.8.0
Requires-Dist: pytz >=2017.3
Requires-Dist: marshmallow
Requires-Dist: marshmallow-dataclass
Requires-Dist: ijson
